zirconium/__init__.py
zirconium/preprocessing.py
pyzirconium-0.0.1.dist-info/LICENSE
pyzirconium-0.0.1.dist-info/METADATA
pyzirconium-0.0.1.dist-info/WHEEL
pyzirconium-0.0.1.dist-info/top_level.txt
pyzirconium-0.0.1.dist-info/RECORD
