Metadata-Version: 2.1
Name: pyzirconium
Version: 0.0.1
Author: Szymon Baluszek, Piotr Michnal
Author-email: Piotr Żarczyński <piotr.zarczynski.06@gmail.com>
License: Copyright 2024 SBaluszek
Project-URL: Homepage, https://github.com/SBaluszek/zirconium
Classifier: License :: OSI Approved :: MIT License
Classifier: Programming Language :: Python :: 3
Requires-Python: >=3.9
License-File: LICENSE
Requires-Dist: numpy
Requires-Dist: scipy
Requires-Dist: scikit-learn
